sqlmigrate/__init__.py
sql_migrate-0.1.0.dist-info/LICENSE
sql_migrate-0.1.0.dist-info/METADATA
sql_migrate-0.1.0.dist-info/WHEEL
sql_migrate-0.1.0.dist-info/top_level.txt
sql_migrate-0.1.0.dist-info/RECORD
