Metadata-Version: 2.1
Name: sql-migrate
Version: 0.1.0
Summary: Write migrations in SQL
Home-page: https://github.com/BlackEarth/sql-migrate
Author: Sean Harrison
Author-email: sah@bookgenesis.com
License: MPL 2.0
Platform: UNKNOWN
Classifier: Development Status :: 1 - Planning
Classifier: Intended Audience :: Developers
Classifier: License :: OSI Approved :: Mozilla Public License 2.0 (MPL 2.0)
Classifier: Programming Language :: Python :: 3
Provides-Extra: test
Provides-Extra: dev
